otaku_watcher/__init__.py
otaku_watcher/anitaku.py
otaku_watcher/tokyo_insider.py
otaku_watcher-1.2.3.dist-info/LICENSE
otaku_watcher-1.2.3.dist-info/METADATA
otaku_watcher-1.2.3.dist-info/WHEEL
otaku_watcher-1.2.3.dist-info/top_level.txt
otaku_watcher-1.2.3.dist-info/RECORD
