Metadata-Version: 2.1
Name: otaku-watcher
Version: 1.2.3
Summary: A mov-cli plugin for watching anime.
License: MIT License
Project-URL: GitHub, https://github.com/JDALab/otaku-watcher
Project-URL: BugTracker, https://github.com/JDALab/otaku-watcher/issues
Keywords: amazing mov-cli plugin
Classifier: Operating System :: Microsoft :: Windows :: Windows 11
Classifier: Operating System :: Microsoft :: Windows :: Windows 10
Classifier: Operating System :: POSIX :: Linux
Classifier: License :: OSI Approved :: MIT License
Classifier: Programming Language :: Python :: 3.8
Classifier: Programming Language :: Python :: 3.9
Classifier: Programming Language :: Python :: 3.10
Classifier: Programming Language :: Python :: 3.11
Requires-Python: >=3.8
License-File: LICENSE
Requires-Dist: requests
Requires-Dist: mov-cli >=4.4
Requires-Dist: thefuzz
Requires-Dist: importlib-metadata ; python_version < "3.8"
Provides-Extra: dev
Requires-Dist: ruff ; extra == 'dev'
Requires-Dist: build ; extra == 'dev'
